{
  "data": {
    "actorModel": {
      "actorName": {
        "asset": "asset/Actor/merchant/Wise Man.actor"
      },
      "girlactor": {
        "asset": "asset/Actor/merchant/Wise Man.actor",
        "selector": "editor/hunter/asset/Actor/merchant/Wise Man.actor"
      },
      "modelType": "Customize"
    },
    "actorName": {
      "asset": "asset/Actor/Redhead Man With Antlers/g2038_pet_02_3.actor"
    },
    "AI_attack": {
      "enable": true
    },
    "AI_patrol": {
      "patrolMode": "randomPath"
    },
    "canClick": true,
    "canJump": false,
    "canMove": false,
    "collision": true,
    "deadSound": {
      "volume": {
        "value": 0
      }
    },
    "girlactor": {
      "asset": "asset/Actor/Antlers Red-Haired Teenager/g2038_pet_02_2.actor"
    },
    "headPic": {
      "asset": "asset/Actor/merchant/村长.png"
    },
    "hideName": true,
    "name": {
      "value": "35621631-93c3-4f6a-ac20-93c32dc4b077"
    },
    "triggers": {
      "list": [
        {
          "actions": [
            {
              "__OBJ_TYPE": "Action_OpenConversation",
              "components": [
                {
                  "__OBJ_TYPE": "Component_Params",
                  "params": [
                    {
                      "value": {
                        "__OBJ_TYPE": "T_Entity",
                        "action": "a6c7e583-addc-457b-b071-2b9bda47af81"
                      }
                    },
                    {
                      "value": {
                        "__OBJ_TYPE": "T_TalkList",
                        "rawval": {
                          "talk": [
                            {
                              "msg": {
                                "value": "3e0d9eb9-7e20-4243-81c6-25fbc9bba54d"
                              },
                              "npc": "myplugin/wise_man"
                            }
                          ]
                        }
                      }
                    },
                    {
                      "value": {
                        "__OBJ_TYPE": "T_OptionList",
                        "rawval": {
                          "option": [
                            {
                              "showText": {
                                "value": "be33e12d-eb46-4cda-b1a8-6130e796e129"
                              },
                              "triggerName": {
                                "value": "optionIsSelected2"
                              }
                            },
                            {
                              "showText": {
                                "value": "760a8349-0fb5-4685-b22e-94e655a6fcaa"
                              }
                            }
                          ]
                        }
                      }
                    },
                    {
                      "value": {
                        "__OBJ_TYPE": "T_EntityEntry",
                        "rawval": "myplugin/wise_man"
                      }
                    }
                  ]
                }
              ],
              "id": {
                "value": "84d91809-03c7-4e31-9e29-ad9907b66f36"
              },
              "pos": {
                "x": 732,
                "y": 146
              }
            },
            {
              "__OBJ_TYPE": "Action_GetContextVar",
              "components": [
                {
                  "__OBJ_TYPE": "Component_Context",
                  "key": "obj2"
                }
              ],
              "id": {
                "value": "a6c7e583-addc-457b-b071-2b9bda47af81"
              },
              "pos": {
                "x": 1390,
                "y": 254
              },
              "type": "T_Entity"
            }
          ],
          "custom_trigger_data": {
            "name": {
              "value": "30a72adb-42fc-43dd-ac39-65aa20d7d068"
            },
            "type": "Trigger_EntityClick"
          },
          "root": {
            "components": [
              {
                "__OBJ_TYPE": "Component_Sequence",
                "children": [
                  {
                    "action": "84d91809-03c7-4e31-9e29-ad9907b66f36"
                  }
                ]
              }
            ],
            "id": {
              "value": "a80292a6-207f-468d-b05d-5c033a819c5e"
            },
            "pos": {
              "x": 396,
              "y": 194
            }
          },
          "type": "Trigger_EntityClick"
        }
      ]
    },
    "unAssailable": true,
    "unDamageable": true
  },
  "meta": {
    "EXPORT": {
      "setting.json": "8c9727351bfa494f40f688af0bd334e9",
      "triggers.bts": "aa8a5ce9041f5cd03ee793443690ce6b"
    },
    "VERSION": "0.24"
  }
}