{
  "data": {
    "castEffect": {
      "effect": {
        "asset": "asset/warrior/123_longzhu1.effect"
      },
      "once": false
    },
    "damage": 6,
    "damagePct": 1,
    "deadRemove": true,
    "name": {
      "value": "buff_intensify"
    },
    "sound": {
      "is3dSound": true,
      "loop": true,
      "sound": {
        "asset": "asset/Sound Assets/aura_01.mp3"
      },
      "volume": {
        "value": 0.53
      }
    },
    "sync": "self"
  },
  "meta": {
    "EXPORT": {
      "setting.json": "3ee8270a8a0316c6a2db6a20ac4e3cfc"
    },
    "VERSION": "0.24"
  }
}